{
  "I Beach Date": "i-beach-date.png",
  "R Alby Ref": "r-alby.png",
  "A ANA-ZERI": "a-14.png",
  "A Asu Neo": "a-asu-neo.png",
  "I Qadrya Cleanup": "i-qadrya-cleanup.png",
  "A Vega": "a-vega.png",
  "A Chrona Arcadian": "a-chrona-arcadian.png",
  "E Full Pack": "e-pack.png",
  "T Lysi Act II": "t-lysi-deuteron.png",
  "A Lysi Act II": "a-lysi-deuteron.png",
  "T Cynthia": "t-egg.png",
  "T Lysi Act I": "t-lysi-prime.png",
  "A Kama Neo": "a-kama-neo.png",
  "T Heart": "t-heart.png"
}
